flame_unsup/__init__.py
flame_unsup/data.py
flame_unsup/data_hcci.py
flame_unsup/double.py
flame_unsup/model.py
flame_unsup/tester.py
flame_unsup/utils.py
flame_unsup/viza.py
flame_unsup_b-1.0.0.dist-info/LICENSE.txt
flame_unsup_b-1.0.0.dist-info/METADATA
flame_unsup_b-1.0.0.dist-info/WHEEL
flame_unsup_b-1.0.0.dist-info/top_level.txt
flame_unsup_b-1.0.0.dist-info/RECORD
